rcer_iot_client_pkg/__init__.py
rcer_iot_client_pkg/general_types/__init__.py
rcer_iot_client_pkg/general_types/api/__init__.py
rcer_iot_client_pkg/general_types/api/update_thies_data_types.py
rcer_iot_client_pkg/general_types/error_types/__init__.py
rcer_iot_client_pkg/general_types/error_types/api/__init__.py
rcer_iot_client_pkg/general_types/error_types/api/update_thies_data_error_types.py
rcer_iot_client_pkg/general_types/error_types/common/__init__.py
rcer_iot_client_pkg/general_types/error_types/common/common_types.py
rcer_iot_client_pkg/libs/ftp_client/__init__.py
rcer_iot_client_pkg/libs/ftp_client/clients/__init__.py
rcer_iot_client_pkg/libs/ftp_client/clients/aioftp_client.py
rcer_iot_client_pkg/libs/ftp_client/ftp_client.py
rcer_iot_client_pkg/libs/ftp_client/ftp_client_contract.py
rcer_iot_client_pkg/libs/ftp_client/types/__init__.py
rcer_iot_client_pkg/libs/ftp_client/types/ftp_client_types.py
rcer_iot_client_pkg/libs/sharepoint_client/__init__.py
rcer_iot_client_pkg/libs/sharepoint_client/clients/sharepoint_rest_api.py
rcer_iot_client_pkg/libs/sharepoint_client/sharepoint_client.py
rcer_iot_client_pkg/libs/sharepoint_client/sharepoint_client_contract.py
rcer_iot_client_pkg/libs/sharepoint_client/types/sharepoint_client_types.py
rcer_iot_client_pkg/libs/zero_dependency/utils/datetime_utils.py
rcer_iot_client_pkg/services/epii/__init__.py
rcer_iot_client_pkg/services/epii/api.py
rcer_iot_client_pkg/services/epii/constants/update_thies_data_constants.py
rcer_iot_client_pkg/services/epii/controllers/__init__.py
rcer_iot_client_pkg/services/epii/controllers/types/__init__.py
rcer_iot_client_pkg/services/epii/controllers/types/update_thies_data_types.py
rcer_iot_client_pkg/services/epii/controllers/update_thies_data.py
rcer_iot_client_pkg/services/epii/use_cases/types/__init__.py
rcer_iot_client_pkg/services/epii/use_cases/types/update_thies_data_types.py
rcer_iot_client_pkg/services/epii/use_cases/update_thies_data.py
rcer_iot_client_pkg-0.6.1.dist-info/LICENSE
rcer_iot_client_pkg-0.6.1.dist-info/METADATA
rcer_iot_client_pkg-0.6.1.dist-info/WHEEL
rcer_iot_client_pkg-0.6.1.dist-info/RECORD
