Metadata-Version: 2.3
Name: rcer_iot_client_pkg
Version: 0.6.1
Summary: A client library for IoT projects in the RCER initiative
License: MIT
Author: pedropablozavalat
Requires-Python: >=3.10,<4.0
Classifier: License :: OSI Approved :: MIT License
Classifier: Programming Language :: Python :: 3
Classifier: Programming Language :: Python :: 3.10
Classifier: Programming Language :: Python :: 3.11
Classifier: Programming Language :: Python :: 3.12
Classifier: Programming Language :: Python :: 3.13
Requires-Dist: aioftp (==0.25.1)
Requires-Dist: aiohttp (==3.11.16)
Requires-Dist: build
Requires-Dist: dotenv (==0.9.9)
Requires-Dist: pydantic (==2.11.3)
Requires-Dist: pytest-cov (==6.1.1)
